pybitrix/__init__.py
pybitrix/pybitrix.py
pybitrix/pybitrix_async.py
PyBitrix-1.2.7.dist-info/LICENSE
PyBitrix-1.2.7.dist-info/METADATA
PyBitrix-1.2.7.dist-info/WHEEL
PyBitrix-1.2.7.dist-info/top_level.txt
PyBitrix-1.2.7.dist-info/RECORD
