Metadata-Version: 2.1
Name: PyBitrix
Version: 1.2.7
Summary: PyBitrix is my lightweight implementation of Bitrix 24 REST API wrapper
Home-page: https://github.com/momoru-kun/PyBitrix
Author: Aleksandr Lenets
Author-email: wowgonit@gmail.com
License: UNKNOWN
Keywords: bitrix24 rest api bx24
Platform: UNKNOWN
Classifier: Development Status :: 5 - Production/Stable
Classifier: Intended Audience :: Developers
Classifier: Natural Language :: Russian
Classifier: Natural Language :: English
Classifier: Topic :: Software Development :: Libraries :: Python Modules
Classifier: Programming Language :: Python :: 3
Classifier: License :: OSI Approved :: MIT License
Classifier: Operating System :: OS Independent
Requires-Python: >=3.5
License-File: LICENSE
Requires-Dist: requests
Requires-Dist: aiohttp
